MANIFEST.in
README.rst
setup.py
django_sql_debugger.egg-info/PKG-INFO
django_sql_debugger.egg-info/SOURCES.txt
django_sql_debugger.egg-info/dependency_links.txt
django_sql_debugger.egg-info/top_level.txt
sql_debugger/__init__.py
sql_debugger/middleware.py
sql_debugger/backends/.DS_Store
sql_debugger/backends/__init__.py
sql_debugger/backends/mysql/.DS_Store
sql_debugger/backends/mysql/__init__.py
sql_debugger/backends/mysql/base.py
sql_debugger/templates/.DS_Store
sql_debugger/templates/sql_debugger/base.html
sql_debugger/templatetags/.DS_Store
sql_debugger/templatetags/__init__.py
sql_debugger/templatetags/__init__.pyc
sql_debugger/templatetags/sql_debug_info.py
sql_debugger/templatetags/sql_debug_info.pyc