Metadata-Version: 1.1
Name: django-sql-debugger
Version: 0.1
Summary: Django app that helps controlling database requests count
Home-page: https://github.com/katharine-kinn/django-sql-debugger
Author: Catherine
Author-email: katherine.goncharova@gmail.com
License: MIT License
Download-URL: https://github.com/katharine-kinn/django-sql-debugger/tarball/0.1
Platform: UNKNOWN
Classifier: Environment :: Web Environment
Classifier: Framework :: Django
Classifier: Intended Audience :: Developers
Classifier: License :: OSI Approved :: MIT License
Classifier: Operating System :: OS Independent
Classifier: Programming Language :: Python
Classifier: Programming Language :: Python :: 2
Classifier: Programming Language :: Python :: 2.6
Classifier: Programming Language :: Python :: 2.7
